chapkit/__init__.py
chapkit/alembic/__init__.py
chapkit/alembic/env.py
chapkit/alembic/script.py.mako
chapkit/alembic/versions/20251010_0927_4d869b5fb06e_initial_schema.py
chapkit/alembic/versions/__init__.py
chapkit/alembic_helpers.py
chapkit/api/__init__.py
chapkit/api/dependencies.py
chapkit/api/service_builder.py
chapkit/artifact/__init__.py
chapkit/artifact/manager.py
chapkit/artifact/models.py
chapkit/artifact/repository.py
chapkit/artifact/router.py
chapkit/artifact/schemas.py
chapkit/cli/__init__.py
chapkit/cli/__main__.py
chapkit/cli/artifact.py
chapkit/cli/cli.py
chapkit/cli/init.py
chapkit/cli/templates/.gitignore
chapkit/cli/templates/Dockerfile.jinja2
chapkit/cli/templates/README.md.jinja2
chapkit/cli/templates/compose.monitoring.yml.jinja2
chapkit/cli/templates/compose.yml.jinja2
chapkit/cli/templates/main.py.jinja2
chapkit/cli/templates/main_shell.py.jinja2
chapkit/cli/templates/main_task.py.jinja2
chapkit/cli/templates/monitoring/grafana/dashboards/chapkit-service-metrics.json
chapkit/cli/templates/monitoring/grafana/provisioning/dashboards/dashboard.yml
chapkit/cli/templates/monitoring/grafana/provisioning/datasources/prometheus.yml
chapkit/cli/templates/monitoring/prometheus/prometheus.yml.jinja2
chapkit/cli/templates/postman_collection_ml.json.jinja2
chapkit/cli/templates/postman_collection_ml_shell.json.jinja2
chapkit/cli/templates/postman_collection_task.json.jinja2
chapkit/cli/templates/pyproject.toml.jinja2
chapkit/cli/templates/scripts/predict_model.py.jinja2
chapkit/cli/templates/scripts/train_model.py.jinja2
chapkit/config/__init__.py
chapkit/config/manager.py
chapkit/config/models.py
chapkit/config/repository.py
chapkit/config/router.py
chapkit/config/schemas.py
chapkit/data/__init__.py
chapkit/data/dataframe.py
chapkit/ml/__init__.py
chapkit/ml/manager.py
chapkit/ml/router.py
chapkit/ml/runner.py
chapkit/ml/schemas.py
chapkit/py.typed
chapkit/scheduler.py
chapkit/task/__init__.py
chapkit/task/executor.py
chapkit/task/registry.py
chapkit-0.12.4.dist-info/WHEEL
chapkit-0.12.4.dist-info/entry_points.txt
chapkit-0.12.4.dist-info/METADATA
chapkit-0.12.4.dist-info/RECORD
