Metadata-Version: 2.3
Name: chapkit
Version: 0.12.4
Summary: ML and data service modules built on servicekit - config, artifacts, tasks, and ML workflows
Keywords: ml,machine-learning,data-science,artifacts,tasks,config,servicekit
Author: Morten Hansen
Author-email: Morten Hansen <morten@dhis2.org>
License: AGPL-3.0-or-later
Classifier: Development Status :: 3 - Alpha
Classifier: Intended Audience :: Developers
Classifier: License :: OSI Approved :: GNU Affero General Public License v3 or later (AGPLv3+)
Classifier: Programming Language :: Python :: 3
Classifier: Programming Language :: Python :: 3.13
Classifier: Framework :: FastAPI
Classifier: Topic :: Software Development :: Libraries :: Python Modules
Classifier: Topic :: Scientific/Engineering :: Artificial Intelligence
Requires-Dist: geojson-pydantic>=2.1.0
Requires-Dist: typer>=0.21.0
Requires-Dist: jinja2>=3.1.6
Requires-Dist: servicekit>=0.6.0
Requires-Dist: httpx>=0.28.1
Requires-Dist: pandas>=2.3.3 ; extra == 'dataframe'
Requires-Dist: polars>=1.34.0 ; extra == 'dataframe'
Requires-Dist: xarray>=2025.10.1 ; extra == 'dataframe'
Requires-Dist: pandas>=2.3.3 ; extra == 'pandas'
Requires-Dist: polars>=1.34.0 ; extra == 'polars'
Requires-Dist: xarray>=2025.10.1 ; extra == 'xarray'
Requires-Dist: pandas>=2.3.3 ; extra == 'xarray'
Requires-Python: >=3.13
Project-URL: Documentation, https://dhis2-chap.github.io/chapkit
Project-URL: Homepage, https://github.com/dhis2-chap/chapkit
Project-URL: Issues, https://github.com/dhis2-chap/chapkit/issues
Project-URL: Repository, https://github.com/dhis2-chap/chapkit
Provides-Extra: dataframe
Provides-Extra: pandas
Provides-Extra: polars
Provides-Extra: xarray
